MANIFEST.in
README.md
setup.py
pyfastcopy/__init__.py
pyfastcopy.egg-info/PKG-INFO
pyfastcopy.egg-info/SOURCES.txt
pyfastcopy.egg-info/dependency_links.txt
pyfastcopy.egg-info/top_level.txt