Metadata-Version: 1.1
Name: pyfastcopy
Version: 1.0.3
Summary: Speed up shutil.copyfile by using sendfile system call
Home-page: https://github.com/desbma/pyfastcopy
Author: desbma
Author-email: UNKNOWN
License: UNKNOWN
Download-URL: https://github.com/desbma/pyfastcopy/archive/1.0.3.tar.gz
Keywords: shutil,copy,copyfile,file,performance,speed,sendfile
Platform: UNKNOWN
Classifier: Development Status :: 4 - Beta
Classifier: Intended Audience :: Developers
Classifier: License :: OSI Approved :: Python Software Foundation License
Classifier: Operating System :: Unix
Classifier: Programming Language :: Python
Classifier: Programming Language :: Python :: 2
Classifier: Programming Language :: Python :: 2.7
Classifier: Programming Language :: Python :: 3
Classifier: Programming Language :: Python :: 3.0
Classifier: Programming Language :: Python :: 3.1
Classifier: Programming Language :: Python :: 3.2
Classifier: Programming Language :: Python :: 3.3
Classifier: Programming Language :: Python :: 3.4
Classifier: Programming Language :: Python :: 3.5
Classifier: Programming Language :: Python :: 3.6
Classifier: Topic :: Software Development :: Libraries :: Python Modules
